README.rst
setup.py
blockhash/__init__.py
blockhash/mains.py
blockhash.egg-info/PKG-INFO
blockhash.egg-info/SOURCES.txt
blockhash.egg-info/dependency_links.txt
blockhash.egg-info/entry_points.txt
blockhash.egg-info/top_level.txt