Metadata-Version: 1.1
Name: blockhash
Version: 0.1.0
Summary: Speed up your SHA. A different hash style
Home-page: https://github.com/Spockuto/blockhash
Author: Venkkatesh_Sekar
Author-email: venkythesupersaiyan@gmail.com
License: UNKNOWN
Keywords: CLI,python
Platform: UNKNOWN
Classifier: Operating System :: POSIX
Classifier: Environment :: Console
Classifier: Programming Language :: Python
Classifier: Programming Language :: Python :: 2
Classifier: Programming Language :: Python :: 3
Classifier: Programming Language :: Python :: 3.2
Classifier: Programming Language :: Python :: 3.3
Classifier: Topic :: Utilities
Classifier: Topic :: Software Development :: Libraries :: Python Modules
